Metadata-Version: 2.1
Name: dbrw
Version: 0.1.14
Summary: DataBase Reader and Writer utilities
Home-page: https://github.com/xtruan/dbrw
Author: Struan Clark
Author-email: dbrw@to.scrk.net
Classifier: Programming Language :: Python :: 3
Classifier: License :: OSI Approved :: MIT License
Classifier: Operating System :: OS Independent
Requires-Python: >=3.6
Provides-Extra: psycopg2
Provides-Extra: psycopg2-binary
License-File: LICENSE
